st_chat_message/__init__.py
st_chat_message/frontend/out/404.html
st_chat_message/frontend/out/_next/static/6ygvE_r4CKVPLu_JlsWil/_buildManifest.js
st_chat_message/frontend/out/_next/static/6ygvE_r4CKVPLu_JlsWil/_ssgManifest.js
st_chat_message/frontend/out/_next/static/chunks/175675d1-280cba64f0247428.js
st_chat_message/frontend/out/_next/static/chunks/framework-5e8ac8dd643904dd.js
st_chat_message/frontend/out/_next/static/chunks/main-c6459c6dbdcff8e8.js
st_chat_message/frontend/out/_next/static/chunks/pages/_app-345c8177130438ac.js
st_chat_message/frontend/out/_next/static/chunks/pages/_error-3f6d1c55bb8051ab.js
st_chat_message/frontend/out/_next/static/chunks/pages/index-df2a1fafbbf92047.js
st_chat_message/frontend/out/_next/static/chunks/polyfills-78c92fac7aa8fdd8.js
st_chat_message/frontend/out/_next/static/chunks/webpack-9d2bee59a0ebae7b.js
st_chat_message/frontend/out/_next/static/css/1f759626be541cb1.css
st_chat_message/frontend/out/_next/static/css/ecb6d8ff2db7565c.css
st_chat_message/frontend/out/_next/static/media/KaTeX_AMS-Regular.1608a09b.woff
st_chat_message/frontend/out/_next/static/media/KaTeX_AMS-Regular.4aafdb68.ttf
st_chat_message/frontend/out/_next/static/media/KaTeX_AMS-Regular.a79f1c31.woff2
st_chat_message/frontend/out/_next/static/media/KaTeX_Caligraphic-Bold.b6770918.woff
st_chat_message/frontend/out/_next/static/media/KaTeX_Caligraphic-Bold.cce5b8ec.ttf
st_chat_message/frontend/out/_next/static/media/KaTeX_Caligraphic-Bold.ec17d132.woff2
st_chat_message/frontend/out/_next/static/media/KaTeX_Caligraphic-Regular.07ef19e7.ttf
st_chat_message/frontend/out/_next/static/media/KaTeX_Caligraphic-Regular.55fac258.woff2
st_chat_message/frontend/out/_next/static/media/KaTeX_Caligraphic-Regular.dad44a7f.woff
st_chat_message/frontend/out/_next/static/media/KaTeX_Fraktur-Bold.9f256b85.woff
st_chat_message/frontend/out/_next/static/media/KaTeX_Fraktur-Bold.b18f59e1.ttf
st_chat_message/frontend/out/_next/static/media/KaTeX_Fraktur-Bold.d42a5579.woff2
st_chat_message-0.3.8.dist-info/WHEEL
st_chat_message-0.3.8.dist-info/METADATA
st_chat_message-0.3.8.dist-info/RECORD
